features/__init__.py
features/authentication.py
features/chat.py
features/chat_analytics.py
features/encryption.py
features/esa256.py
features/file_upload.py
features/get_external_user.py
features/message_handling.py
features/moderation.py
features/notifications.py
features/presence.py
features/reactions.py
features/read_receipts.py
features/room_management.py
features/search_text.py
features/security.py
features/session.py
features/status_management.py
features/typing_indicators.py
features/user_profiles.py
mocks/__init__.py
mocks/mock_external_api.py
mocks/mock_mongodb.py
mocks/mock_websocket.py
tests/__init__.py
tests/conftest.py
tests/text_main.py
tests/unit/__init__.py
tests/unit/test_authentication.py
tests/unit/test_message_handling.py
tests/unit/test_mongodb_connection.py
tests/unit/test_room_management.py
ultrachatapp/__init__.py
ultrachatapp/config.py
ultrachatapp/constants.py
ultrachatapp/database_client.py
ultrachatapp/main.py
ultrachatapp/models.py
ultrachatapp/test.py
ultrachatapp-0.1.4.dist-info/METADATA
ultrachatapp-0.1.4.dist-info/WHEEL
ultrachatapp-0.1.4.dist-info/top_level.txt
ultrachatapp-0.1.4.dist-info/RECORD
